{"errors":[],"warnings":[],"namedChunkGroups":{"app":{"chunks":[6,2],"assets":["webpack-runtime-7296454c26d49b14c8e5.js","webpack-runtime-7296454c26d49b14c8e5.js.map","app-43f2f1181a739d6c9ff5.js","app-43f2f1181a739d6c9ff5.js.map"],"children":{},"childAssets":{}},"component---src-pages-404-js":{"chunks":[0,1,3],"assets":["styles.8c205d58230387c0c0b3.css","styles-8169b9847cc84f528336.js","styles-8169b9847cc84f528336.js.map","1-0521586239af26644c9d.js","1-0521586239af26644c9d.js.map","component---src-pages-404-js-1481d3bda499b82ab5bf.js","component---src-pages-404-js-1481d3bda499b82ab5bf.js.map"],"children":{},"childAssets":{}},"component---src-pages-index-js":{"chunks":[0,1,4],"assets":["styles.8c205d58230387c0c0b3.css","styles-8169b9847cc84f528336.js","styles-8169b9847cc84f528336.js.map","1-0521586239af26644c9d.js","1-0521586239af26644c9d.js.map","component---src-pages-index-js-73dda9b46ab41be2da3a.js","component---src-pages-index-js-73dda9b46ab41be2da3a.js.map"],"children":{},"childAssets":{}},"component---src-pages-page-2-js":{"chunks":[0,1,5],"assets":["styles.8c205d58230387c0c0b3.css","styles-8169b9847cc84f528336.js","styles-8169b9847cc84f528336.js.map","1-0521586239af26644c9d.js","1-0521586239af26644c9d.js.map","component---src-pages-page-2-js-99f8972d9061268e8afd.js","component---src-pages-page-2-js-99f8972d9061268e8afd.js.map"],"children":{},"childAssets":{}}},"assetsByChunkName":{"app":["webpack-runtime-7296454c26d49b14c8e5.js","app-43f2f1181a739d6c9ff5.js"],"component---src-pages-404-js":["styles.8c205d58230387c0c0b3.css","styles-8169b9847cc84f528336.js","1-0521586239af26644c9d.js","component---src-pages-404-js-1481d3bda499b82ab5bf.js"],"component---src-pages-index-js":["styles.8c205d58230387c0c0b3.css","styles-8169b9847cc84f528336.js","1-0521586239af26644c9d.js","component---src-pages-index-js-73dda9b46ab41be2da3a.js"],"component---src-pages-page-2-js":["styles.8c205d58230387c0c0b3.css","styles-8169b9847cc84f528336.js","1-0521586239af26644c9d.js","component---src-pages-page-2-js-99f8972d9061268e8afd.js"]}}